<?xml version="1.0" encoding="UTF-8"?>
<document>
<data id="history">
<metadata>
<columns>
<column name="BOARDID" type="string" bytes="12" max_size="0" />
<column name="TRADEDATE" type="date" bytes="10" max_size="0" />
<column name="SHORTNAME" type="string" bytes="189" max_size="0" />
<column name="SECID" type="string" bytes="36" max_size="0" />
<column name="NUMTRADES" type="double" />
<column name="VALUE" type="double" />
<column name="OPEN" type="double" />
<column name="LOW" type="double" />
<column name="HIGH" type="double" />
<column name="LEGALCLOSEPRICE" type="double" />
<column name="WAPRICE" type="double" />
<column name="CLOSE" type="double" />
<column name="VOLUME" type="double" />
<column name="MARKETPRICE2" type="double" />
<column name="MARKETPRICE3" type="double" />
<column name="ADMITTEDQUOTE" type="double" />
<column name="MP2VALTRD" type="double" />
<column name="MARKETPRICE3TRADESVALUE" type="double" />
<column name="ADMITTEDVALUE" type="double" />
<column name="WAVAL" type="double" />
</columns>
</metadata>
<rows>
<row BOARDID="TQIF" TRADEDATE="2020-04-15" SHORTNAME="ПИФБКС Осн" SECID="RU000A0JP799" NUMTRADES="16" VALUE="490874" OPEN="242.6" LOW="240.6" HIGH="248" LEGALCLOSEPRICE="247" WAPRICE="246.6" CLOSE="247" VOLUME="1990" MARKETPRICE2="" MARKETPRICE3="246.4" ADMITTEDQUOTE="247" MP2VALTRD="0" MARKETPRICE3TRADESVALUE="557078" ADMITTEDVALUE="0" WAVAL="" />
<row BOARDID="TQIF" TRADEDATE="2020-04-15" SHORTNAME="ПИФРВМ-Лог" SECID="RU000A0JPCF8" NUMTRADES="0" VALUE="0" OPEN="" LOW="" HIGH="" LEGALCLOSEPRICE="950" WAPRICE="" CLOSE="" VOLUME="0" MARKETPRICE2="" MARKETPRICE3="" ADMITTEDQUOTE="950" MP2VALTRD="0" MARKETPRICE3TRADESVALUE="0" ADMITTEDVALUE="0" WAVAL="" />
<row BOARDID="TQIF" TRADEDATE="2020-04-15" SHORTNAME="ПИФОткрОбл" SECID="RU000A0JPKJ3" NUMTRADES="0" VALUE="0" OPEN="" LOW="" HIGH="" LEGALCLOSEPRICE="" WAPRICE="" CLOSE="" VOLUME="0" MARKETPRICE2="" MARKETPRICE3="" ADMITTEDQUOTE="" MP2VALTRD="0" MARKETPRICE3TRADESVALUE="0" ADMITTEDVALUE="0" WAVAL="" />
<row BOARDID="TQIF" TRADEDATE="2020-04-15" SHORTNAME="ПИФ РВМ" SECID="RU000A0JPLG7" NUMTRADES="0" VALUE="0" OPEN="" LOW="" HIGH="" LEGALCLOSEPRICE="200" WAPRICE="" CLOSE="" VOLUME="0" MARKETPRICE2="" MARKETPRICE3="" ADMITTEDQUOTE="200" MP2VALTRD="0" MARKETPRICE3TRADESVALUE="0" ADMITTEDVALUE="0" WAVAL="" />
<row BOARDID="TQIF" TRADEDATE="2020-04-15" SHORTNAME="ПИФРусТрнз" SECID="RU000A0JPM71" NUMTRADES="0" VALUE="0" OPEN="" LOW="" HIGH="" LEGALCLOSEPRICE="69400" WAPRICE="" CLOSE="" VOLUME="0" MARKETPRICE2="" MARKETPRICE3="" ADMITTEDQUOTE="69400" MP2VALTRD="0" MARKETPRICE3TRADESVALUE="0" ADMITTEDVALUE="0" WAVAL="" />
<row BOARDID="TQIF" TRADEDATE="2020-04-15" SHORTNAME="ОРЕОЛПроек" SECID="RU000A0JPWL4" NUMTRADES="0" VALUE="0" OPEN="" LOW="" HIGH="" LEGALCLOSEPRICE="98500" WAPRICE="" CLOSE="" VOLUME="0" MARKETPRICE2="" MARKETPRICE3="" ADMITTEDQUOTE="98500" MP2VALTRD="0" MARKETPRICE3TRADESVALUE="0" ADMITTEDVALUE="0" WAVAL="" />
<row BOARDID="TQIF" TRADEDATE="2020-04-15" SHORTNAME="МихРентИП" SECID="RU000A0JPY69" NUMTRADES="0" VALUE="0" OPEN="" LOW="" HIGH="" LEGALCLOSEPRICE="985" WAPRICE="" CLOSE="" VOLUME="0" MARKETPRICE2="" MARKETPRICE3="" ADMITTEDQUOTE="985" MP2VALTRD="0" MARKETPRICE3TRADESVALUE="0" ADMITTEDVALUE="0" WAVAL="" />
<row BOARDID="TQIF" TRADEDATE="2020-04-15" SHORTNAME="ТрнфИП ТрЭ" SECID="RU000A0JQ4Q8" NUMTRADES="0" VALUE="0" OPEN="" LOW="" HIGH="" LEGALCLOSEPRICE="1040" WAPRICE="" CLOSE="" VOLUME="0" MARKETPRICE2="" MARKETPRICE3="" ADMITTEDQUOTE="1040" MP2VALTRD="0" MARKETPRICE3TRADESVALUE="0" ADMITTEDVALUE="0" WAVAL="" />
<row BOARDID="TQIF" TRADEDATE="2020-04-15" SHORTNAME="ЗПИФАтлант" SECID="RU000A0JQ797" NUMTRADES="0" VALUE="0" OPEN="" LOW="" HIGH="" LEGALCLOSEPRICE="5330000" WAPRICE="" CLOSE="" VOLUME="0" MARKETPRICE2="" MARKETPRICE3="" ADMITTEDQUOTE="5330000" MP2VALTRD="0" MARKETPRICE3TRADESVALUE="0" ADMITTEDVALUE="0" WAVAL="" />
<row BOARDID="TQIF" TRADEDATE="2020-04-15" SHORTNAME="ЗПИФ Рент2" SECID="RU000A0JQPA9" NUMTRADES="0" VALUE="0" OPEN="" LOW="" HIGH="" LEGALCLOSEPRICE="526000" WAPRICE="" CLOSE="" VOLUME="0" MARKETPRICE2="" MARKETPRICE3="" ADMITTEDQUOTE="526000" MP2VALTRD="0" MARKETPRICE3TRADESVALUE="0" ADMITTEDVALUE="0" WAVAL="" />
<row BOARDID="TQIF" TRADEDATE="2020-04-15" SHORTNAME="ПИФЮгра" SECID="RU000A0JQSM8" NUMTRADES="0" VALUE="0" OPEN="" LOW="" HIGH="" LEGALCLOSEPRICE="11800" WAPRICE="" CLOSE="" VOLUME="0" MARKETPRICE2="" MARKETPRICE3="" ADMITTEDQUOTE="11800" MP2VALTRD="0" MARKETPRICE3TRADESVALUE="0" ADMITTEDVALUE="0" WAVAL="" />
<row BOARDID="TQIF" TRADEDATE="2020-04-15" SHORTNAME="РВММегаплс" SECID="RU000A0JQYE3" NUMTRADES="0" VALUE="0" OPEN="" LOW="" HIGH="" LEGALCLOSEPRICE="284000" WAPRICE="" CLOSE="" VOLUME="0" MARKETPRICE2="" MARKETPRICE3="" ADMITTEDQUOTE="284000" MP2VALTRD="0" MARKETPRICE3TRADESVALUE="0" ADMITTEDVALUE="0" WAVAL="" />
<row BOARDID="TQIF" TRADEDATE="2020-04-15" SHORTNAME="ПИФТверУс" SECID="RU000A0JR0A9" NUMTRADES="0" VALUE="0" OPEN="" LOW="" HIGH="" LEGALCLOSEPRICE="33000" WAPRICE="" CLOSE="" VOLUME="0" MARKETPRICE2="32900" MARKETPRICE3="33000" ADMITTEDQUOTE="33000" MP2VALTRD="82455500" MARKETPRICE3TRADESVALUE="56465900" ADMITTEDVALUE="82455500" WAVAL="" />
<row BOARDID="TQIF" TRADEDATE="2020-04-15" SHORTNAME="ВТБФондАкц" SECID="RU000A0JR282" NUMTRADES="60" VALUE="2740525" OPEN="30.15" LOW="30.15" HIGH="32.75" LEGALCLOSEPRICE="30.8" WAPRICE="30.95" CLOSE="30.8" VOLUME="88500" MARKETPRICE2="30.95" MARKETPRICE3="30.95" ADMITTEDQUOTE="30.8" MP2VALTRD="2740525" MARKETPRICE3TRADESVALUE="2740525" ADMITTEDVALUE="2740525" WAVAL="" />
<row BOARDID="TQIF" TRADEDATE="2020-04-15" SHORTNAME="ВТБИнМсБир" SECID="RU000A0JR290" NUMTRADES="120" VALUE="3870310" OPEN="6135" LOW="5860" HIGH="6155" LEGALCLOSEPRICE="5860" WAPRICE="6000" CLOSE="5870" VOLUME="645" MARKETPRICE2="6000" MARKETPRICE3="6000" ADMITTEDQUOTE="5860" MP2VALTRD="3870310" MARKETPRICE3TRADESVALUE="3870310" ADMITTEDVALUE="3870310" WAVAL="" />
<row BOARDID="TQIF" TRADEDATE="2020-04-15" SHORTNAME="ВТБФондСб" SECID="RU000A0JR2A5" NUMTRADES="0" VALUE="0" OPEN="" LOW="" HIGH="" LEGALCLOSEPRICE="14.55" WAPRICE="" CLOSE="" VOLUME="0" MARKETPRICE2="" MARKETPRICE3="" ADMITTEDQUOTE="14.55" MP2VALTRD="0" MARKETPRICE3TRADESVALUE="0" ADMITTEDVALUE="0" WAVAL="" />
<row BOARDID="TQIF" TRADEDATE="2020-04-15" SHORTNAME="ВТБФондКаз" SECID="RU000A0JR2C1" NUMTRADES="92" VALUE="1445221" OPEN="69.6" LOW="68" HIGH="69.6" LEGALCLOSEPRICE="68.8" WAPRICE="69.2" CLOSE="68.2" VOLUME="20870" MARKETPRICE2="69.2" MARKETPRICE3="69.2" ADMITTEDQUOTE="68.8" MP2VALTRD="1445221" MARKETPRICE3TRADESVALUE="1445221" ADMITTEDVALUE="1445221" WAVAL="" />
<row BOARDID="TQIF" TRADEDATE="2020-04-15" SHORTNAME="ПИФАльтИнв" SECID="RU000A0JR316" NUMTRADES="0" VALUE="0" OPEN="" LOW="" HIGH="" LEGALCLOSEPRICE="282000" WAPRICE="" CLOSE="" VOLUME="0" MARKETPRICE2="" MARKETPRICE3="" ADMITTEDQUOTE="282000" MP2VALTRD="0" MARKETPRICE3TRADESVALUE="0" ADMITTEDVALUE="0" WAVAL="" />
<row BOARDID="TQIF" TRADEDATE="2020-04-15" SHORTNAME="ПИФТФГСпек" SECID="RU000A0JR3X5" NUMTRADES="0" VALUE="0" OPEN="" LOW="" HIGH="" LEGALCLOSEPRICE="775" WAPRICE="" CLOSE="" VOLUME="0" MARKETPRICE2="" MARKETPRICE3="" ADMITTEDQUOTE="775" MP2VALTRD="0" MARKETPRICE3TRADESVALUE="0" ADMITTEDVALUE="0" WAVAL="" />
<row BOARDID="TQIF" TRADEDATE="2020-04-15" SHORTNAME="ПИФ АТРИУМ" SECID="RU000A0JRHC0" NUMTRADES="0" VALUE="0" OPEN="" LOW="" HIGH="" LEGALCLOSEPRICE="1220" WAPRICE="" CLOSE="" VOLUME="0" MARKETPRICE2="" MARKETPRICE3="" ADMITTEDQUOTE="1220" MP2VALTRD="0" MARKETPRICE3TRADESVALUE="0" ADMITTEDVALUE="0" WAVAL="" />
<row BOARDID="TQIF" TRADEDATE="2020-04-15" SHORTNAME="ПИФСистИнв" SECID="RU000A0JRNZ9" NUMTRADES="0" VALUE="0" OPEN="" LOW="" HIGH="" LEGALCLOSEPRICE="249000" WAPRICE="" CLOSE="" VOLUME="0" MARKETPRICE2="" MARKETPRICE3="" ADMITTEDQUOTE="249000" MP2VALTRD="0" MARKETPRICE3TRADESVALUE="0" ADMITTEDVALUE="0" WAVAL="" />
<row BOARDID="TQIF" TRADEDATE="2020-04-15" SHORTNAME="АГАНА САкт" SECID="RU000A0JRQT5" NUMTRADES="0" VALUE="0" OPEN="" LOW="" HIGH="" LEGALCLOSEPRICE="75500" WAPRICE="" CLOSE="" VOLUME="0" MARKETPRICE2="" MARKETPRICE3="" ADMITTEDQUOTE="75500" MP2VALTRD="0" MARKETPRICE3TRADESVALUE="0" ADMITTEDVALUE="0" WAVAL="" />
<row BOARDID="TQIF" TRADEDATE="2020-04-15" SHORTNAME="ПИФТретЗем" SECID="RU000A0JRST1" NUMTRADES="0" VALUE="0" OPEN="" LOW="" HIGH="" LEGALCLOSEPRICE="11000" WAPRICE="" CLOSE="" VOLUME="0" MARKETPRICE2="" MARKETPRICE3="" ADMITTEDQUOTE="11000" MP2VALTRD="0" MARKETPRICE3TRADESVALUE="0" ADMITTEDVALUE="0" WAVAL="" />
<row BOARDID="TQIF" TRADEDATE="2020-04-15" SHORTNAME="ТринфПерсп" SECID="RU000A0JRTR3" NUMTRADES="0" VALUE="0" OPEN="" LOW="" HIGH="" LEGALCLOSEPRICE="730" WAPRICE="" CLOSE="" VOLUME="0" MARKETPRICE2="" MARKETPRICE3="" ADMITTEDQUOTE="730" MP2VALTRD="0" MARKETPRICE3TRADESVALUE="0" ADMITTEDVALUE="0" WAVAL="" />
<row BOARDID="TQIF" TRADEDATE="2020-04-15" SHORTNAME="ПИФЧетвЗем" SECID="RU000A0JRXV7" NUMTRADES="0" VALUE="0" OPEN="" LOW="" HIGH="" LEGALCLOSEPRICE="20300" WAPRICE="" CLOSE="" VOLUME="0" MARKETPRICE2="" MARKETPRICE3="" ADMITTEDQUOTE="20300" MP2VALTRD="0" MARKETPRICE3TRADESVALUE="0" ADMITTEDVALUE="0" WAVAL="" />
<row BOARDID="TQIF" TRADEDATE="2020-04-15" SHORTNAME="ПИФКоммИнв" SECID="RU000A0JS991" NUMTRADES="0" VALUE="0" OPEN="" LOW="" HIGH="" LEGALCLOSEPRICE="1835" WAPRICE="" CLOSE="" VOLUME="0" MARKETPRICE2="" MARKETPRICE3="" ADMITTEDQUOTE="1835" MP2VALTRD="0" MARKETPRICE3TRADESVALUE="0" ADMITTEDVALUE="0" WAVAL="" />
<row BOARDID="TQIF" TRADEDATE="2020-04-15" SHORTNAME="РВМСтНедв1" SECID="RU000A0JS9A9" NUMTRADES="0" VALUE="0" OPEN="" LOW="" HIGH="" LEGALCLOSEPRICE="189000" WAPRICE="" CLOSE="" VOLUME="0" MARKETPRICE2="" MARKETPRICE3="" ADMITTEDQUOTE="189000" MP2VALTRD="0" MARKETPRICE3TRADESVALUE="0" ADMITTEDVALUE="0" WAVAL="" />
<row BOARDID="TQIF" TRADEDATE="2020-04-15" SHORTNAME="ЗПИФКрасн" SECID="RU000A0JSGF3" NUMTRADES="0" VALUE="0" OPEN="" LOW="" HIGH="" LEGALCLOSEPRICE="10500" WAPRICE="" CLOSE="" VOLUME="0" MARKETPRICE2="" MARKETPRICE3="" ADMITTEDQUOTE="10500" MP2VALTRD="0" MARKETPRICE3TRADESVALUE="0" ADMITTEDVALUE="0" WAVAL="" />
<row BOARDID="TQIF" TRADEDATE="2020-04-15" SHORTNAME="ТФГ-руб.об" SECID="RU000A0JT7G9" NUMTRADES="0" VALUE="0" OPEN="" LOW="" HIGH="" LEGALCLOSEPRICE="320" WAPRICE="" CLOSE="" VOLUME="0" MARKETPRICE2="" MARKETPRICE3="" ADMITTEDQUOTE="320" MP2VALTRD="0" MARKETPRICE3TRADESVALUE="0" ADMITTEDVALUE="0" WAVAL="" />
<row BOARDID="TQIF" TRADEDATE="2020-04-15" SHORTNAME="ПИФУрлНед1" SECID="RU000A0JT8U8" NUMTRADES="0" VALUE="0" OPEN="" LOW="" HIGH="" LEGALCLOSEPRICE="" WAPRICE="" CLOSE="" VOLUME="0" MARKETPRICE2="" MARKETPRICE3="" ADMITTEDQUOTE="" MP2VALTRD="0" MARKETPRICE3TRADESVALUE="0" ADMITTEDVALUE="0" WAVAL="" />
<row BOARDID="TQIF" TRADEDATE="2020-04-15" SHORTNAME="ПИФПятЗем" SECID="RU000A0JTPA3" NUMTRADES="0" VALUE="0" OPEN="" LOW="" HIGH="" LEGALCLOSEPRICE="10800" WAPRICE="" CLOSE="" VOLUME="0" MARKETPRICE2="" MARKETPRICE3="" ADMITTEDQUOTE="10800" MP2VALTRD="0" MARKETPRICE3TRADESVALUE="0" ADMITTEDVALUE="0" WAVAL="" />
<row BOARDID="TQDE" TRADEDATE="2020-04-15" SHORTNAME="ИСУ-2" SECID="RU000A0JTXM2" NUMTRADES="0" VALUE="0" OPEN="" LOW="" HIGH="" LEGALCLOSEPRICE="1095000" WAPRICE="" CLOSE="" VOLUME="0" MARKETPRICE2="" MARKETPRICE3="" ADMITTEDQUOTE="1095000" MP2VALTRD="0" MARKETPRICE3TRADESVALUE="0" ADMITTEDVALUE="0" WAVAL="" />
<row BOARDID="TQIF" TRADEDATE="2020-04-15" SHORTNAME="ПИФПерПрК" SECID="RU000A0JU0G1" NUMTRADES="0" VALUE="0" OPEN="" LOW="" HIGH="" LEGALCLOSEPRICE="2050" WAPRICE="" CLOSE="" VOLUME="0" MARKETPRICE2="" MARKETPRICE3="" ADMITTEDQUOTE="2050" MP2VALTRD="0" MARKETPRICE3TRADESVALUE="0" ADMITTEDVALUE="0" WAVAL="" />
<row BOARDID="TQIF" TRADEDATE="2020-04-15" SHORTNAME="ПИФКонкЭст" SECID="RU000A0JUDS9" NUMTRADES="0" VALUE="0" OPEN="" LOW="" HIGH="" LEGALCLOSEPRICE="106000" WAPRICE="" CLOSE="" VOLUME="0" MARKETPRICE2="" MARKETPRICE3="" ADMITTEDQUOTE="106000" MP2VALTRD="0" MARKETPRICE3TRADESVALUE="0" ADMITTEDVALUE="0" WAVAL="" />
<row BOARDID="TQIF" TRADEDATE="2020-04-15" SHORTNAME="ПИФРВМКап" SECID="RU000A0JUKK1" NUMTRADES="0" VALUE="0" OPEN="" LOW="" HIGH="" LEGALCLOSEPRICE="" WAPRICE="" CLOSE="" VOLUME="0" MARKETPRICE2="" MARKETPRICE3="" ADMITTEDQUOTE="" MP2VALTRD="0" MARKETPRICE3TRADESVALUE="0" ADMITTEDVALUE="0" WAVAL="" />
<row BOARDID="TQDE" TRADEDATE="2020-04-15" SHORTNAME="ИСУ-ПН" SECID="RU000A0JUQZ6" NUMTRADES="0" VALUE="0" OPEN="" LOW="" HIGH="" LEGALCLOSEPRICE="20400" WAPRICE="" CLOSE="" VOLUME="0" MARKETPRICE2="" MARKETPRICE3="19800" ADMITTEDQUOTE="20400" MP2VALTRD="0" MARKETPRICE3TRADESVALUE="49755700" ADMITTEDVALUE="0" WAVAL="" />
<row BOARDID="TQIF" TRADEDATE="2020-04-15" SHORTNAME="ПИФНМТраст" SECID="RU000A0JUR20" NUMTRADES="0" VALUE="0" OPEN="" LOW="" HIGH="" LEGALCLOSEPRICE="566000" WAPRICE="" CLOSE="" VOLUME="0" MARKETPRICE2="" MARKETPRICE3="" ADMITTEDQUOTE="566000" MP2VALTRD="0" MARKETPRICE3TRADESVALUE="0" ADMITTEDVALUE="0" WAVAL="" />
<row BOARDID="TQIF" TRADEDATE="2020-04-15" SHORTNAME="ПИФ КОНСЕР" SECID="RU000A0JUR61" NUMTRADES="0" VALUE="0" OPEN="" LOW="" HIGH="" LEGALCLOSEPRICE="1680" WAPRICE="" CLOSE="" VOLUME="0" MARKETPRICE2="" MARKETPRICE3="" ADMITTEDQUOTE="1680" MP2VALTRD="0" MARKETPRICE3TRADESVALUE="0" ADMITTEDVALUE="0" WAVAL="" />
<row BOARDID="TQIF" TRADEDATE="2020-04-15" SHORTNAME="Рф-МосБгф" SECID="RU000A0JURB5" NUMTRADES="1" VALUE="229200" OPEN="19100" LOW="19100" HIGH="19100" LEGALCLOSEPRICE="19100" WAPRICE="19100" CLOSE="19100" VOLUME="12" MARKETPRICE2="" MARKETPRICE3="18860" ADMITTEDQUOTE="19100" MP2VALTRD="0" MARKETPRICE3TRADESVALUE="528340" ADMITTEDVALUE="0" WAVAL="" />
<row BOARDID="TQIF" TRADEDATE="2020-04-15" SHORTNAME="Рент.Недв." SECID="RU000A0JUZ61" NUMTRADES="0" VALUE="0" OPEN="" LOW="" HIGH="" LEGALCLOSEPRICE="" WAPRICE="" CLOSE="" VOLUME="0" MARKETPRICE2="" MARKETPRICE3="" ADMITTEDQUOTE="" MP2VALTRD="0" MARKETPRICE3TRADESVALUE="0" ADMITTEDVALUE="0" WAVAL="" />
<row BOARDID="TQDE" TRADEDATE="2020-04-15" SHORTNAME="ИСУ ГК-3" SECID="RU000A0JVEZ0" NUMTRADES="0" VALUE="0" OPEN="" LOW="" HIGH="" LEGALCLOSEPRICE="3000" WAPRICE="" CLOSE="" VOLUME="0" MARKETPRICE2="" MARKETPRICE3="" ADMITTEDQUOTE="3000" MP2VALTRD="0" MARKETPRICE3TRADESVALUE="0" ADMITTEDVALUE="0" WAVAL="" />
<row BOARDID="TQIF" TRADEDATE="2020-04-15" SHORTNAME="ПИФБКС Имп" SECID="RU000A0JVHY6" NUMTRADES="10" VALUE="164225" OPEN="241.5" LOW="233" HIGH="241.5" LEGALCLOSEPRICE="240.5" WAPRICE="238" CLOSE="240.5" VOLUME="690" MARKETPRICE2="" MARKETPRICE3="238" ADMITTEDQUOTE="240.5" MP2VALTRD="0" MARKETPRICE3TRADESVALUE="535415" ADMITTEDVALUE="0" WAVAL="" />
<row BOARDID="TQDE" TRADEDATE="2020-04-15" SHORTNAME="ИСУ ЕФГ-3" SECID="RU000A0JVT35" NUMTRADES="0" VALUE="0" OPEN="" LOW="" HIGH="" LEGALCLOSEPRICE="400" WAPRICE="" CLOSE="" VOLUME="0" MARKETPRICE2="" MARKETPRICE3="" ADMITTEDQUOTE="400" MP2VALTRD="0" MARKETPRICE3TRADESVALUE="0" ADMITTEDVALUE="0" WAVAL="" />
<row BOARDID="TQIF" TRADEDATE="2020-04-15" SHORTNAME="СберАрБизн" SECID="RU000A0JWAW3" NUMTRADES="0" VALUE="0" OPEN="" LOW="" HIGH="" LEGALCLOSEPRICE="304000" WAPRICE="" CLOSE="" VOLUME="0" MARKETPRICE2="" MARKETPRICE3="" ADMITTEDQUOTE="304000" MP2VALTRD="0" MARKETPRICE3TRADESVALUE="0" ADMITTEDVALUE="0" WAVAL="" />
<row BOARDID="TQIF" TRADEDATE="2020-04-15" SHORTNAME="ПИФ РубОбл" SECID="RU000A0JX1H4" NUMTRADES="8" VALUE="91584" OPEN="1696" LOW="1696" HIGH="1696" LEGALCLOSEPRICE="1696" WAPRICE="1696" CLOSE="1696" VOLUME="54" MARKETPRICE2="" MARKETPRICE3="1696" ADMITTEDQUOTE="1696" MP2VALTRD="0" MARKETPRICE3TRADESVALUE="620682" ADMITTEDVALUE="0" WAVAL="" />
<row BOARDID="TQIF" TRADEDATE="2020-04-15" SHORTNAME="ПИФ РосАкц" SECID="RU000A0JX2H2" NUMTRADES="0" VALUE="0" OPEN="" LOW="" HIGH="" LEGALCLOSEPRICE="" WAPRICE="" CLOSE="" VOLUME="0" MARKETPRICE2="" MARKETPRICE3="" ADMITTEDQUOTE="" MP2VALTRD="0" MARKETPRICE3TRADESVALUE="0" ADMITTEDVALUE="0" WAVAL="" />
<row BOARDID="TQIF" TRADEDATE="2020-04-15" SHORTNAME="ЗПИФДОМ.РФ" SECID="RU000A0JXP78" NUMTRADES="1" VALUE="2480" OPEN="1240" LOW="1240" HIGH="1240" LEGALCLOSEPRICE="1240" WAPRICE="1240" CLOSE="1240" VOLUME="2" MARKETPRICE2="" MARKETPRICE3="" ADMITTEDQUOTE="1240" MP2VALTRD="0" MARKETPRICE3TRADESVALUE="0" ADMITTEDVALUE="0" WAVAL="" />
<row BOARDID="TQIF" TRADEDATE="2020-04-15" SHORTNAME="СберАрБиз2" SECID="RU000A0ZYC64" NUMTRADES="0" VALUE="0" OPEN="" LOW="" HIGH="" LEGALCLOSEPRICE="312000" WAPRICE="" CLOSE="" VOLUME="0" MARKETPRICE2="" MARKETPRICE3="" ADMITTEDQUOTE="312000" MP2VALTRD="0" MARKETPRICE3TRADESVALUE="0" ADMITTEDVALUE="0" WAVAL="" />
<row BOARDID="TQIF" TRADEDATE="2020-04-15" SHORTNAME="ПИФНевХаус" SECID="RU000A0ZYF79" NUMTRADES="0" VALUE="0" OPEN="" LOW="" HIGH="" LEGALCLOSEPRICE="" WAPRICE="" CLOSE="" VOLUME="0" MARKETPRICE2="" MARKETPRICE3="" ADMITTEDQUOTE="" MP2VALTRD="0" MARKETPRICE3TRADESVALUE="0" ADMITTEDVALUE="0" WAVAL="" />
<row BOARDID="TQIF" TRADEDATE="2020-04-15" SHORTNAME="ЛобняЗПИФ" SECID="RU000A0ZZ422" NUMTRADES="0" VALUE="0" OPEN="" LOW="" HIGH="" LEGALCLOSEPRICE="338320" WAPRICE="" CLOSE="" VOLUME="0" MARKETPRICE2="" MARKETPRICE3="" ADMITTEDQUOTE="338320" MP2VALTRD="0" MARKETPRICE3TRADESVALUE="0" ADMITTEDVALUE="0" WAVAL="" />
<row BOARDID="TQIF" TRADEDATE="2020-04-15" SHORTNAME="СОЛИДСР2ЗП" SECID="RU000A0ZZX84" NUMTRADES="0" VALUE="0" OPEN="" LOW="" HIGH="" LEGALCLOSEPRICE="" WAPRICE="" CLOSE="" VOLUME="0" MARKETPRICE2="" MARKETPRICE3="" ADMITTEDQUOTE="" MP2VALTRD="0" MARKETPRICE3TRADESVALUE="0" ADMITTEDVALUE="0" WAVAL="" />
<row BOARDID="TQIF" TRADEDATE="2020-04-15" SHORTNAME="СберДен ОП" SECID="RU000A1002D0" NUMTRADES="4" VALUE="19540572" OPEN="1143" LOW="1137" HIGH="1143" LEGALCLOSEPRICE="1137" WAPRICE="1137" CLOSE="1137" VOLUME="17186" MARKETPRICE2="1137.6" MARKETPRICE3="1137.6" ADMITTEDQUOTE="1137" MP2VALTRD="21991993.2" MARKETPRICE3TRADESVALUE="21991993.2" ADMITTEDVALUE="21991993.2" WAVAL="" />
<row BOARDID="TQIF" TRADEDATE="2020-04-15" SHORTNAME="Регион РРГ" SECID="RU000A100U05" NUMTRADES="0" VALUE="0" OPEN="" LOW="" HIGH="" LEGALCLOSEPRICE="" WAPRICE="" CLOSE="" VOLUME="0" MARKETPRICE2="" MARKETPRICE3="" ADMITTEDQUOTE="" MP2VALTRD="0" MARKETPRICE3TRADESVALUE="0" ADMITTEDVALUE="0" WAVAL="" />
<row BOARDID="TQIF" TRADEDATE="2020-04-15" SHORTNAME="ОПИФФридСИ" SECID="RU000A100ZY1" NUMTRADES="0" VALUE="0" OPEN="" LOW="" HIGH="" LEGALCLOSEPRICE="21250" WAPRICE="" CLOSE="" VOLUME="0" MARKETPRICE2="" MARKETPRICE3="" ADMITTEDQUOTE="21250" MP2VALTRD="0" MARKETPRICE3TRADESVALUE="0" ADMITTEDVALUE="0" WAVAL="" />
<row BOARDID="SMAL" TRADEDATE="2020-04-15" SHORTNAME="RUSAL plc" SECID="RUAL" NUMTRADES="1" VALUE="153.24" OPEN="25.54" LOW="25.54" HIGH="25.54" LEGALCLOSEPRICE="" WAPRICE="25.18" CLOSE="25.54" VOLUME="6" MARKETPRICE2="" MARKETPRICE3="" ADMITTEDQUOTE="" MP2VALTRD="0" MARKETPRICE3TRADESVALUE="0" ADMITTEDVALUE="0" WAVAL="" />
<row BOARDID="TQBR" TRADEDATE="2020-04-15" SHORTNAME="RUSAL plc" SECID="RUAL" NUMTRADES="16066" VALUE="399067813.15" OPEN="25.8" LOW="24.72" HIGH="25.8" LEGALCLOSEPRICE="24.975" WAPRICE="25.18" CLOSE="24.975" VOLUME="15849260" MARKETPRICE2="25.18" MARKETPRICE3="25.18" ADMITTEDQUOTE="24.975" MP2VALTRD="399067813.15" MARKETPRICE3TRADESVALUE="399067813.15" ADMITTEDVALUE="399067813.15" WAVAL="" />
<row BOARDID="TQBR" TRADEDATE="2020-04-15" SHORTNAME="Русгрэйн" SECID="RUGR" NUMTRADES="2236" VALUE="3239393.36" OPEN="7.99" LOW="7.528" HIGH="8.15" LEGALCLOSEPRICE="7.55" WAPRICE="7.772" CLOSE="7.55" VOLUME="416830" MARKETPRICE2="7.772" MARKETPRICE3="7.772" ADMITTEDQUOTE="7.55" MP2VALTRD="3239393.36" MARKETPRICE3TRADESVALUE="3239393.36" ADMITTEDVALUE="3239393.36" WAVAL="" />
<row BOARDID="TQTD" TRADEDATE="2020-04-15" SHORTNAME="RUSB ETF" SECID="RUSB" NUMTRADES="0" VALUE="0" OPEN="" LOW="" HIGH="" LEGALCLOSEPRICE="28.53" WAPRICE="28.2" CLOSE="" VOLUME="0" MARKETPRICE2="2067.5" MARKETPRICE3="2067.5" ADMITTEDQUOTE="28.53" MP2VALTRD="4861185.09" MARKETPRICE3TRADESVALUE="4861185.09" ADMITTEDVALUE="4861185.09" WAVAL="74580.79" />
<row BOARDID="TQTE" TRADEDATE="2020-04-15" SHORTNAME="RUSB ETF" SECID="RUSB" NUMTRADES="6" VALUE="806" OPEN="26" LOW="26" HIGH="26" LEGALCLOSEPRICE="26.11" WAPRICE="25.81" CLOSE="26" VOLUME="31" MARKETPRICE2="2067.5" MARKETPRICE3="2067.5" ADMITTEDQUOTE="26.11" MP2VALTRD="4861185.09" MARKETPRICE3TRADESVALUE="4861185.09" ADMITTEDVALUE="4861185.09" WAVAL="67616.35" />
<row BOARDID="TQTF" TRADEDATE="2020-04-15" SHORTNAME="RUSB ETF" SECID="RUSB" NUMTRADES="263" VALUE="4796609.5" OPEN="2075.5" LOW="1977.5" HIGH="2100" LEGALCLOSEPRICE="2091.5" WAPRICE="2067.5" CLOSE="2091.5" VOLUME="2320" MARKETPRICE2="2067.5" MARKETPRICE3="2067.5" ADMITTEDQUOTE="2091.5" MP2VALTRD="4861185.09" MARKETPRICE3TRADESVALUE="4861185.09" ADMITTEDVALUE="4861185.09" WAVAL="5797351.4" />
<row BOARDID="TQTD" TRADEDATE="2020-04-15" SHORTNAME="RUSE ETF" SECID="RUSE" NUMTRADES="4" VALUE="277.49" OPEN="21.22" LOW="21.22" HIGH="22" LEGALCLOSEPRICE="21.41" WAPRICE="21.67" CLOSE="21.3" VOLUME="13" MARKETPRICE2="1589" MARKETPRICE3="1589" ADMITTEDQUOTE="21.41" MP2VALTRD="4819610.1" MARKETPRICE3TRADESVALUE="4819610.1" ADMITTEDVALUE="4819610.1" WAVAL="148343.24" />
<row BOARDID="TQTE" TRADEDATE="2020-04-15" SHORTNAME="RUSE ETF" SECID="RUSE" NUMTRADES="2" VALUE="38.96" OPEN="19.48" LOW="19.48" HIGH="19.48" LEGALCLOSEPRICE="19.59" WAPRICE="19.83" CLOSE="19.48" VOLUME="2" MARKETPRICE2="1589" MARKETPRICE3="1589" ADMITTEDQUOTE="19.59" MP2VALTRD="4819610.1" MARKETPRICE3TRADESVALUE="4819610.1" ADMITTEDVALUE="4819610.1" WAVAL="134490.78" />
<row BOARDID="TQTF" TRADEDATE="2020-04-15" SHORTNAME="RUSE ETF" SECID="RUSE" NUMTRADES="537" VALUE="4796144.5" OPEN="1652.5" LOW="1556.5" HIGH="1652.5" LEGALCLOSEPRICE="1569.5" WAPRICE="1589" CLOSE="1570" VOLUME="3018" MARKETPRICE2="1589" MARKETPRICE3="1589" ADMITTEDQUOTE="1569.5" MP2VALTRD="4819610.1" MARKETPRICE3TRADESVALUE="4819610.1" ADMITTEDVALUE="4819610.1" WAVAL="11531091.16" />
<row BOARDID="TQBR" TRADEDATE="2020-04-15" SHORTNAME="ИКРУСС-ИНВ" SECID="RUSI" NUMTRADES="22" VALUE="99480" OPEN="40.5" LOW="38.8" HIGH="40.5" LEGALCLOSEPRICE="38.8" WAPRICE="39.8" CLOSE="38.8" VOLUME="2500" MARKETPRICE2="" MARKETPRICE3="40.2" ADMITTEDQUOTE="38.8" MP2VALTRD="0" MARKETPRICE3TRADESVALUE="530110" ADMITTEDVALUE="0" WAVAL="" />
<row BOARDID="SMAL" TRADEDATE="2020-04-15" SHORTNAME="Русполимет" SECID="RUSP" NUMTRADES="1" VALUE="323.57" OPEN="0.555" LOW="0.555" HIGH="0.555" LEGALCLOSEPRICE="" WAPRICE="0.678" CLOSE="0.555" VOLUME="583" MARKETPRICE2="" MARKETPRICE3="" ADMITTEDQUOTE="" MP2VALTRD="0" MARKETPRICE3TRADESVALUE="0" ADMITTEDVALUE="0" WAVAL="" />
<row BOARDID="TQBR" TRADEDATE="2020-04-15" SHORTNAME="Русполимет" SECID="RUSP" NUMTRADES="1177" VALUE="17975650" OPEN="0.623" LOW="0.6005" HIGH="0.75" LEGALCLOSEPRICE="0.6195" WAPRICE="0.678" CLOSE="0.6195" VOLUME="26520000" MARKETPRICE2="0.678" MARKETPRICE3="0.678" ADMITTEDQUOTE="0.6195" MP2VALTRD="17975650" MARKETPRICE3TRADESVALUE="17975650" ADMITTEDVALUE="17975650" WAVAL="" />
<row BOARDID="SMAL" TRADEDATE="2020-04-15" SHORTNAME="РязЭнСб" SECID="RZSB" NUMTRADES="1" VALUE="6.47" OPEN="6.47" LOW="6.47" HIGH="6.47" LEGALCLOSEPRICE="" WAPRICE="6.18" CLOSE="6.47" VOLUME="1" MARKETPRICE2="" MARKETPRICE3="" ADMITTEDQUOTE="" MP2VALTRD="0" MARKETPRICE3TRADESVALUE="0" ADMITTEDVALUE="0" WAVAL="" />
<row BOARDID="TQBR" TRADEDATE="2020-04-15" SHORTNAME="РязЭнСб" SECID="RZSB" NUMTRADES="19" VALUE="197660" OPEN="6.13" LOW="6.1" HIGH="6.29" LEGALCLOSEPRICE="6.18" WAPRICE="6.18" CLOSE="6.18" VOLUME="32000" MARKETPRICE2="" MARKETPRICE3="6.21" ADMITTEDQUOTE="6.18" MP2VALTRD="0" MARKETPRICE3TRADESVALUE="615140" ADMITTEDVALUE="0" WAVAL="" />
<row BOARDID="TQBR" TRADEDATE="2020-04-15" SHORTNAME="СамарЭн-ао" SECID="SAGO" NUMTRADES="4" VALUE="18640" OPEN="0.38" LOW="0.366" HIGH="0.38" LEGALCLOSEPRICE="0.368" WAPRICE="0.374" CLOSE="0.366" VOLUME="50000" MARKETPRICE2="" MARKETPRICE3="0.382" ADMITTEDQUOTE="0.368" MP2VALTRD="0" MARKETPRICE3TRADESVALUE="507580" ADMITTEDVALUE="0" WAVAL="" />
<row BOARDID="TQBR" TRADEDATE="2020-04-15" SHORTNAME="СамарЭн-ап" SECID="SAGOP" NUMTRADES="8" VALUE="32710" OPEN="0.365" LOW="0.361" HIGH="0.369" LEGALCLOSEPRICE="0.361" WAPRICE="0.363" CLOSE="0.361" VOLUME="90000" MARKETPRICE2="" MARKETPRICE3="0.366" ADMITTEDQUOTE="0.361" MP2VALTRD="0" MARKETPRICE3TRADESVALUE="500850" ADMITTEDVALUE="0" WAVAL="" />
<row BOARDID="TQBR" TRADEDATE="2020-04-15" SHORTNAME="СаратЭн-ао" SECID="SARE" NUMTRADES="8" VALUE="54992" OPEN="0.11" LOW="0.1098" HIGH="0.11" LEGALCLOSEPRICE="0.11" WAPRICE="0.11" CLOSE="0.11" VOLUME="500000" MARKETPRICE2="" MARKETPRICE3="0.1128" ADMITTEDQUOTE="0.11" MP2VALTRD="0" MARKETPRICE3TRADESVALUE="591308" ADMITTEDVALUE="0" WAVAL="" />
<row BOARDID="TQBR" TRADEDATE="2020-04-15" SHORTNAME="СаратЭн-ап" SECID="SAREP" NUMTRADES="12" VALUE="13258" OPEN="0.0834" LOW="0.0824" HIGH="0.0834" LEGALCLOSEPRICE="0.0824" WAPRICE="0.083" CLOSE="0.0824" VOLUME="160000" MARKETPRICE2="" MARKETPRICE3="0.0894" ADMITTEDQUOTE="0.0824" MP2VALTRD="0" MARKETPRICE3TRADESVALUE="518348" ADMITTEDVALUE="0" WAVAL="" />
<row BOARDID="TQTD" TRADEDATE="2020-04-15" SHORTNAME="SBCB ETF" SECID="SBCB" NUMTRADES="0" VALUE="0" OPEN="" LOW="" HIGH="" LEGALCLOSEPRICE="16.87" WAPRICE="16.69" CLOSE="" VOLUME="0" MARKETPRICE2="1223.8" MARKETPRICE3="1223.8" ADMITTEDQUOTE="16.87" MP2VALTRD="4370110.6" MARKETPRICE3TRADESVALUE="4370110.6" ADMITTEDVALUE="4370110.6" WAVAL="57252.29" />
<row BOARDID="TQTF" TRADEDATE="2020-04-15" SHORTNAME="SBCB ETF" SECID="SBCB" NUMTRADES="249" VALUE="4370110.6" OPEN="1212" LOW="1210" HIGH="1243.2" LEGALCLOSEPRICE="1236.6" WAPRICE="1223.8" CLOSE="1236.6" VOLUME="3571" MARKETPRICE2="1223.8" MARKETPRICE3="1223.8" ADMITTEDQUOTE="1236.6" MP2VALTRD="4370110.6" MARKETPRICE3TRADESVALUE="4370110.6" ADMITTEDVALUE="4370110.6" WAVAL="4450364.01" />
<row BOARDID="SMAL" TRADEDATE="2020-04-15" SHORTNAME="Сбербанк" SECID="SBER" NUMTRADES="23" VALUE="10654.87" OPEN="197" LOW="187.6" HIGH="198.98" LEGALCLOSEPRICE="" WAPRICE="190.2" CLOSE="195" VOLUME="55" MARKETPRICE2="" MARKETPRICE3="" ADMITTEDQUOTE="" MP2VALTRD="0" MARKETPRICE3TRADESVALUE="0" ADMITTEDVALUE="0" WAVAL="" />
<row BOARDID="SPEQ" TRADEDATE="2020-04-15" SHORTNAME="Сбербанк" SECID="SBER" NUMTRADES="0" VALUE="0" OPEN="" LOW="" HIGH="" LEGALCLOSEPRICE="" WAPRICE="" CLOSE="" VOLUME="0" MARKETPRICE2="" MARKETPRICE3="" ADMITTEDQUOTE="" MP2VALTRD="0" MARKETPRICE3TRADESVALUE="0" ADMITTEDVALUE="0" WAVAL="" />
<row BOARDID="TQBR" TRADEDATE="2020-04-15" SHORTNAME="Сбербанк" SECID="SBER" NUMTRADES="125257" VALUE="18670648932.7" OPEN="196" LOW="186.06" HIGH="196.25" LEGALCLOSEPRICE="186.07" WAPRICE="190.2" CLOSE="186.07" VOLUME="98164460" MARKETPRICE2="190.2" MARKETPRICE3="190.2" ADMITTEDQUOTE="186.07" MP2VALTRD="18670648932.7" MARKETPRICE3TRADESVALUE="18670648932.7" ADMITTEDVALUE="18670648932.7" WAVAL="" />
<row BOARDID="SMAL" TRADEDATE="2020-04-15" SHORTNAME="Сбербанк-п" SECID="SBERP" NUMTRADES="33" VALUE="11156.34" OPEN="178.58" LOW="172" HIGH="186.12" LEGALCLOSEPRICE="" WAPRICE="174.53" CLOSE="172" VOLUME="63" MARKETPRICE2="" MARKETPRICE3="" ADMITTEDQUOTE="" MP2VALTRD="0" MARKETPRICE3TRADESVALUE="0" ADMITTEDVALUE="0" WAVAL="" />
<row BOARDID="SPEQ" TRADEDATE="2020-04-15" SHORTNAME="Сбербанк-п" SECID="SBERP" NUMTRADES="0" VALUE="0" OPEN="" LOW="" HIGH="" LEGALCLOSEPRICE="" WAPRICE="" CLOSE="" VOLUME="0" MARKETPRICE2="" MARKETPRICE3="" ADMITTEDQUOTE="" MP2VALTRD="0" MARKETPRICE3TRADESVALUE="0" ADMITTEDVALUE="0" WAVAL="" />
<row BOARDID="TQBR" TRADEDATE="2020-04-15" SHORTNAME="Сбербанк-п" SECID="SBERP" NUMTRADES="48704" VALUE="2641637239.8" OPEN="178.8" LOW="171" HIGH="179.5" LEGALCLOSEPRICE="172" WAPRICE="174.53" CLOSE="172" VOLUME="15135580" MARKETPRICE2="174.53" MARKETPRICE3="174.53" ADMITTEDQUOTE="172" MP2VALTRD="2641637239.8" MARKETPRICE3TRADESVALUE="2641637239.8" ADMITTEDVALUE="2641637239.8" WAVAL="" />
<row BOARDID="TQTF" TRADEDATE="2020-04-15" SHORTNAME="SBGB ETF" SECID="SBGB" NUMTRADES="133" VALUE="20708491.8" OPEN="1145.8" LOW="1145.8" HIGH="1169.4" LEGALCLOSEPRICE="1165.8" WAPRICE="1165.4" CLOSE="1163" VOLUME="17771" MARKETPRICE2="1165.2" MARKETPRICE3="1165.2" ADMITTEDQUOTE="1165.8" MP2VALTRD="20708491.8" MARKETPRICE3TRADESVALUE="20708491.8" ADMITTEDVALUE="20708491.8" WAVAL="46755463.19" />
<row BOARDID="TQTF" TRADEDATE="2020-04-15" SHORTNAME="SBMX ETF" SECID="SBMX" NUMTRADES="1746" VALUE="42205055.5" OPEN="1228.5" LOW="1154.5" HIGH="1228.5" LEGALCLOSEPRICE="1160" WAPRICE="1181" CLOSE="1164" VOLUME="35734" MARKETPRICE2="1181" MARKETPRICE3="1181" ADMITTEDQUOTE="1160" MP2VALTRD="42205055.5" MARKETPRICE3TRADESVALUE="42205055.5" ADMITTEDVALUE="42205055.5" WAVAL="60168033.8" />
<row BOARDID="TQTF" TRADEDATE="2020-04-15" SHORTNAME="SBRB ETF" SECID="SBRB" NUMTRADES="111" VALUE="11937321.5" OPEN="1057.5" LOW="1045.3" HIGH="1057.5" LEGALCLOSEPRICE="1045.3" WAPRICE="1052" CLOSE="1045.3" VOLUME="11347" MARKETPRICE2="1052" MARKETPRICE3="1052" ADMITTEDQUOTE="1045.3" MP2VALTRD="11937321.5" MARKETPRICE3TRADESVALUE="11937321.5" ADMITTEDVALUE="11937321.5" WAVAL="3543229.42" />
<row BOARDID="TQTD" TRADEDATE="2020-04-15" SHORTNAME="SBSP ETF" SECID="SBSP" NUMTRADES="69" VALUE="25692.8" OPEN="14.99" LOW="14.5" HIGH="15" LEGALCLOSEPRICE="14.88" WAPRICE="14.97" CLOSE="14.5" VOLUME="1743" MARKETPRICE2="1097.2" MARKETPRICE3="1097.2" ADMITTEDQUOTE="14.88" MP2VALTRD="23843754.23" MARKETPRICE3TRADESVALUE="23843754.23" ADMITTEDVALUE="23843754.23" WAVAL="109219.67" />
<row BOARDID="TQTF" TRADEDATE="2020-04-15" SHORTNAME="SBSP ETF" SECID="SBSP" NUMTRADES="608" VALUE="21960086.6" OPEN="1095" LOW="1090.2" HIGH="1106" LEGALCLOSEPRICE="1090.6" WAPRICE="1097.4" CLOSE="1106" VOLUME="19987" MARKETPRICE2="1097.2" MARKETPRICE3="1097.2" ADMITTEDQUOTE="1090.6" MP2VALTRD="23843754.23" MARKETPRICE3TRADESVALUE="23843754.23" ADMITTEDVALUE="23843754.23" WAVAL="8489917.89" />
<row BOARDID="SMAL" TRADEDATE="2020-04-15" SHORTNAME="Селигдар" SECID="SELG" NUMTRADES="8" VALUE="1232.94" OPEN="22.6" LOW="22.6" HIGH="23.79" LEGALCLOSEPRICE="" WAPRICE="23.42" CLOSE="23.79" VOLUME="52" MARKETPRICE2="" MARKETPRICE3="" ADMITTEDQUOTE="" MP2VALTRD="0" MARKETPRICE3TRADESVALUE="0" ADMITTEDVALUE="0" WAVAL="" />
<row BOARDID="TQBR" TRADEDATE="2020-04-15" SHORTNAME="Селигдар" SECID="SELG" NUMTRADES="5113" VALUE="67089509" OPEN="25.01" LOW="22.25" HIGH="25.1" LEGALCLOSEPRICE="22.84" WAPRICE="23.42" CLOSE="22.84" VOLUME="2864800" MARKETPRICE2="23.42" MARKETPRICE3="23.42" ADMITTEDQUOTE="22.84" MP2VALTRD="67089509" MARKETPRICE3TRADESVALUE="67089509" ADMITTEDVALUE="67089509" WAVAL="" />
<row BOARDID="SMAL" TRADEDATE="2020-04-15" SHORTNAME="Селигдар-п" SECID="SELGP" NUMTRADES="3" VALUE="507.2" OPEN="31.7" LOW="31.7" HIGH="31.7" LEGALCLOSEPRICE="" WAPRICE="28.65" CLOSE="31.7" VOLUME="16" MARKETPRICE2="" MARKETPRICE3="" ADMITTEDQUOTE="" MP2VALTRD="0" MARKETPRICE3TRADESVALUE="0" ADMITTEDVALUE="0" WAVAL="" />
<row BOARDID="TQBR" TRADEDATE="2020-04-15" SHORTNAME="Селигдар-п" SECID="SELGP" NUMTRADES="380" VALUE="4461815" OPEN="30" LOW="27.7" HIGH="30.3" LEGALCLOSEPRICE="28.3" WAPRICE="28.65" CLOSE="28.4" VOLUME="155700" MARKETPRICE2="28.65" MARKETPRICE3="28.65" ADMITTEDQUOTE="28.3" MP2VALTRD="4461815" MARKETPRICE3TRADESVALUE="4461815" ADMITTEDVALUE="4461815" WAVAL="" />
<row BOARDID="SMAL" TRADEDATE="2020-04-15" SHORTNAME="САФМАР ао" SECID="SFIN" NUMTRADES="1" VALUE="2197" OPEN="439.4" LOW="439.4" HIGH="439.4" LEGALCLOSEPRICE="" WAPRICE="449.4" CLOSE="439.4" VOLUME="5" MARKETPRICE2="" MARKETPRICE3="" ADMITTEDQUOTE="" MP2VALTRD="0" MARKETPRICE3TRADESVALUE="0" ADMITTEDVALUE="0" WAVAL="" />
<row BOARDID="TQBR" TRADEDATE="2020-04-15" SHORTNAME="САФМАР ао" SECID="SFIN" NUMTRADES="510" VALUE="5413802" OPEN="449" LOW="446.2" HIGH="454.2" LEGALCLOSEPRICE="446.6" WAPRICE="449.4" CLOSE="446.2" VOLUME="12050" MARKETPRICE2="449.2" MARKETPRICE3="449.2" ADMITTEDQUOTE="446.6" MP2VALTRD="5413802" MARKETPRICE3TRADESVALUE="5413802" ADMITTEDVALUE="5413802" WAVAL="" />
<row BOARDID="TQDE" TRADEDATE="2020-04-15" SHORTNAME="СибГост ао" SECID="SIBG" NUMTRADES="5072" VALUE="17749538.45" OPEN="0.4815" LOW="0.405" HIGH="0.513" LEGALCLOSEPRICE="0.411" WAPRICE="0.447" CLOSE="0.413" VOLUME="39699600" MARKETPRICE2="0.447" MARKETPRICE3="0.447" ADMITTEDQUOTE="0.411" MP2VALTRD="17749538.45" MARKETPRICE3TRADESVALUE="17749538.45" ADMITTEDVALUE="17749538.45" WAVAL="" />
<row BOARDID="SMAL" TRADEDATE="2020-04-15" SHORTNAME="Газпрнефть" SECID="SIBN" NUMTRADES="10" VALUE="7523.3" OPEN="315.6" LOW="310" HIGH="315.65" LEGALCLOSEPRICE="" WAPRICE="311.85" CLOSE="310" VOLUME="24" MARKETPRICE2="" MARKETPRICE3="" ADMITTEDQUOTE="" MP2VALTRD="0" MARKETPRICE3TRADESVALUE="0" ADMITTEDVALUE="0" WAVAL="" />
<row BOARDID="TQBR" TRADEDATE="2020-04-15" SHORTNAME="Газпрнефть" SECID="SIBN" NUMTRADES="16005" VALUE="730211381.5" OPEN="320" LOW="305.1" HIGH="323.25" LEGALCLOSEPRICE="308.2" WAPRICE="311.85" CLOSE="308.2" VOLUME="2341590" MARKETPRICE2="311.85" MARKETPRICE3="311.85" ADMITTEDQUOTE="308.2" MP2VALTRD="730211381.5" MARKETPRICE3TRADESVALUE="730211381.5" ADMITTEDVALUE="730211381.5" WAVAL="" />
<row BOARDID="TQBR" TRADEDATE="2020-04-15" SHORTNAME="Сахэнер ао" SECID="SLEN" NUMTRADES="61" VALUE="304863.5" OPEN="4.1" LOW="4" HIGH="4.11" LEGALCLOSEPRICE="4" WAPRICE="4.075" CLOSE="4.02" VOLUME="74800" MARKETPRICE2="" MARKETPRICE3="4.075" ADMITTEDQUOTE="4" MP2VALTRD="0" MARKETPRICE3TRADESVALUE="500121.5" ADMITTEDVALUE="0" WAVAL="" />
<row BOARDID="SMAL" TRADEDATE="2020-04-15" SHORTNAME="Сургнфгз" SECID="SNGS" NUMTRADES="15" VALUE="4519.35" OPEN="36.975" LOW="33.2" HIGH="36.975" LEGALCLOSEPRICE="" WAPRICE="34.055" CLOSE="33.2" VOLUME="127" MARKETPRICE2="" MARKETPRICE3="" ADMITTEDQUOTE="" MP2VALTRD="0" MARKETPRICE3TRADESVALUE="0" ADMITTEDVALUE="0" WAVAL="" />
<row BOARDID="SPEQ" TRADEDATE="2020-04-15" SHORTNAME="Сургнфгз" SECID="SNGS" NUMTRADES="0" VALUE="0" OPEN="" LOW="" HIGH="" LEGALCLOSEPRICE="" WAPRICE="" CLOSE="" VOLUME="0" MARKETPRICE2="" MARKETPRICE3="" ADMITTEDQUOTE="" MP2VALTRD="0" MARKETPRICE3TRADESVALUE="0" ADMITTEDVALUE="0" WAVAL="" />
<row BOARDID="TQBR" TRADEDATE="2020-04-15" SHORTNAME="Сургнфгз" SECID="SNGS" NUMTRADES="28719" VALUE="3049960172" OPEN="35.115" LOW="33.29" HIGH="35.25" LEGALCLOSEPRICE="33.75" WAPRICE="34.055" CLOSE="33.75" VOLUME="89554700" MARKETPRICE2="34.055" MARKETPRICE3="34.055" ADMITTEDQUOTE="33.75" MP2VALTRD="3049960172" MARKETPRICE3TRADESVALUE="3049960172" ADMITTEDVALUE="3049960172" WAVAL="" />
<row BOARDID="SMAL" TRADEDATE="2020-04-15" SHORTNAME="Сургнфгз-п" SECID="SNGSP" NUMTRADES="8" VALUE="5876.86" OPEN="37.43" LOW="36.95" HIGH="38.6" LEGALCLOSEPRICE="" WAPRICE="37.03" CLOSE="36.95" VOLUME="157" MARKETPRICE2="" MARKETPRICE3="" ADMITTEDQUOTE="" MP2VALTRD="0" MARKETPRICE3TRADESVALUE="0" ADMITTEDVALUE="0" WAVAL="" />
<row BOARDID="SPEQ" TRADEDATE="2020-04-15" SHORTNAME="Сургнфгз-п" SECID="SNGSP" NUMTRADES="0" VALUE="0" OPEN="" LOW="" HIGH="" LEGALCLOSEPRICE="" WAPRICE="" CLOSE="" VOLUME="0" MARKETPRICE2="" MARKETPRICE3="" ADMITTEDQUOTE="" MP2VALTRD="0" MARKETPRICE3TRADESVALUE="0" ADMITTEDVALUE="0" WAVAL="" />
</rows>
</data>
<data id="history.cursor">
<metadata>
<columns>
<column name="INDEX" type="int64" />
<column name="TOTAL" type="int64" />
<column name="PAGESIZE" type="int64" />
</columns>
</metadata>
<rows>
<row INDEX="300" TOTAL="495" PAGESIZE="100" />
</rows>
</data>
</document>
